osmconflator/__init__.py
osmconflator/api.py
osmconflator/conflation.py
osmconflator/utils.py
tests/__init__.py
tests/test_conflation.py
osmconflator-0.0.1.dist-info/LICENSE
osmconflator-0.0.1.dist-info/METADATA
osmconflator-0.0.1.dist-info/WHEEL
osmconflator-0.0.1.dist-info/top_level.txt
osmconflator-0.0.1.dist-info/RECORD
