Metadata-Version: 2.1
Name: osmconflator
Version: 0.0.1
Summary: A package for conflation of GeoJSON features with OSM data
Author: Kshitij Raj Sharma
Author-email: skshitizraj@gmail.com
License: MIT
Classifier: Development Status :: 3 - Alpha
Classifier: License :: OSI Approved :: MIT License
Classifier: Programming Language :: Python :: 3
Classifier: Programming Language :: Python :: 3.6
Classifier: Programming Language :: Python :: 3.7
Classifier: Programming Language :: Python :: 3.8
Classifier: Programming Language :: Python :: 3.9
License-File: LICENSE
Requires-Dist: shapely
Requires-Dist: requests
